any_template.py
any_template-0.2.0.dist-info/LICENSE
any_template-0.2.0.dist-info/METADATA
any_template-0.2.0.dist-info/WHEEL
any_template-0.2.0.dist-info/entry_points.txt
any_template-0.2.0.dist-info/top_level.txt
any_template-0.2.0.dist-info/RECORD
