Metadata-Version: 2.1
Name: any-template
Version: 0.2.0
Summary: A CLI tools to get you started on any project in any language
Home-page: https://github.com/Adwaith-Rajesh/any-template
Author: Adwaith Rajesh
Author-email: adwaithrajesh3180@gmail.com
License: MIT
Platform: UNKNOWN
Classifier: License :: OSI Approved :: MIT License
Classifier: Programming Language :: Python :: 3
Classifier: Programming Language :: Python :: 3 :: Only
Classifier: Programming Language :: Python :: 3.6
Classifier: Programming Language :: Python :: 3.7
Classifier: Programming Language :: Python :: 3.8
Classifier: Programming Language :: Python :: 3.9
Requires-Python: >=3.6.1
License-File: LICENSE
